kuplift/__init__.py
kuplift/bayesian_decision_tree.py
kuplift/bayesian_random_forest.py
kuplift/binary_discretization_functions.py
kuplift/feature_selection.py
kuplift/helperfunctions.py
kuplift/node.py
kuplift/optimized_univariate_encoding.py
kuplift/tree.py
kuplift/umodl_search_algorithm.py
kuplift/univariate_encoding.py
kuplift-0.0.15.dist-info/licenses/LICENSE
kuplift-0.0.15.dist-info/METADATA
kuplift-0.0.15.dist-info/WHEEL
kuplift-0.0.15.dist-info/top_level.txt
kuplift-0.0.15.dist-info/RECORD
