Metadata-Version: 2.4
Name: kuplift
Version: 0.0.15
Summary: A User Parameter-free Bayesian Framework for Uplift Modeling
Maintainer-email: The Khiops Team <khiops.team@orange.com>
Requires-Python: >=3.9
License-File: LICENSE
Requires-Dist: numpy>=2.0.2
Requires-Dist: pandas>=2.3.3
Requires-Dist: sortedcontainers>=2.4.0
Requires-Dist: scikit-learn>=1.6.1
Requires-Dist: khiops<11.0.0.0,>=10.3.2.1
Requires-Dist: umodl>=0.0.28
Provides-Extra: docs
Requires-Dist: sphinx>=5.3.0; extra == "docs"
Requires-Dist: furo>=0.22.2; extra == "docs"
Requires-Dist: numpydoc>=1.5.0; extra == "docs"
Requires-Dist: sphinx-copybutton>=0.5.0; extra == "docs"
Requires-Dist: tomlkit>=0.14.0; extra == "docs"
Provides-Extra: test
Requires-Dist: pytest>=8.4.2; extra == "test"
Dynamic: license-file
